{"version": "4.4.0", "objects": [{"type": "rect", "version": "4.4.0", "originX": "left", "originY": "top", "left": -5.12, "top": 17.08, "width": 861, "height": 17, "fill": "rgba(200, 169, 110, 0.15)", "stroke": "#c8a96e", "strokeWidth": 2, "strokeDashArray": null, "strokeLineCap": "butt", "strokeDashOffset": 0, "strokeLineJoin": "miter", "strokeUniform": true, "strokeMiterLimit": 4, "scaleX": 1, "scaleY": 1.07, "angle": 358.64, "flipX": false, "flipY": false, "opacity": 1, "shadow": null, "visible": true, "backgroundColor": "", "fillRule": "nonzero", "paintFirst": "fill", "globalCompositeOperation": "source-over", "skewX": 0, "skewY": 0, "rx": 0, "ry": 0}, {"type": "rect", "version": "4.4.0", "originX": "left", "originY": "top", "left": 5.9, "top": 30.68, "width": 708, "height": 15, "fill": "rgba(200, 169, 110, 0.15)", "stroke": "#c8a96e", "strokeWidth": 2, "strokeDashArray": null, "strokeLineCap": "butt", "strokeDashOffset": 0, "strokeLineJoin": "miter", "strokeUniform": true, "strokeMiterLimit": 4, "scaleX": 1, "scaleY": 1, "angle": 358.92, "flipX": false, "flipY": false, "opacity": 1, "shadow": null, "visible": true, "backgroundColor": "", "fillRule": "nonzero", "paintFirst": "fill", "globalCompositeOperation": "source-over", "skewX": 0, "skewY": 0, "rx": 0, "ry": 0}, {"type": "rect", "version": "4.4.0", "originX": "left", "originY": "top", "left": -3.07, "top": 45.27, "width": 716, "height": 13, "fill": "rgba(200, 169, 110, 0.15)", "stroke": "#c8a96e", "strokeWidth": 2, "strokeDashArray": null, "strokeLineCap": "butt", "strokeDashOffset": 0, "strokeLineJoin": "miter", "strokeUniform": true, "strokeMiterLimit": 4, "scaleX": 1.01, "scaleY": 1.16, "angle": 359.47, "flipX": false, "flipY": false, "opacity": 1, "shadow": null, "visible": true, "backgroundColor": "", "fillRule": "nonzero", "paintFirst": "fill", "globalCompositeOperation": "source-over", "skewX": 0, "skewY": 0, "rx": 0, "ry": 0}, {"type": "rect", "version": "4.4.0", "originX": "left", "originY": "top", "left": 8.99, "top": 58.15, "width": 705, "height": 20, "fill": "rgba(200, 169, 110, 0.15)", "stroke": "#c8a96e", "strokeWidth": 2, "strokeDashArray": null, "strokeLineCap": "butt", "strokeDashOffset": 0, "strokeLineJoin": "miter", "strokeUniform": true, "strokeMiterLimit": 4, "scaleX": 1, "scaleY": 0.66, "angle": 358.81, "flipX": false, "flipY": false, "opacity": 1, "shadow": null, "visible": true, "backgroundColor": "", "fillRule": "nonzero", "paintFirst": "fill", "globalCompositeOperation": "source-over", "skewX": 0, "skewY": 0, "rx": 0, "ry": 0}, {"type": "rect", "version": "4.4.0", "originX": "left", "originY": "top", "left": 548, "top": 64, "width": 165, "height": 16, "fill": "rgba(200, 169, 110, 0.15)", "stroke": "#c8a96e", "strokeWidth": 2, "strokeDashArray": null, "strokeLineCap": "butt", "strokeDashOffset": 0, "strokeLineJoin": "miter", "strokeUniform": true, "strokeMiterLimit": 4, "scaleX": 1, "scaleY": 1, "angle": 0, "flipX": false, "flipY": false, "opacity": 1, "shadow": null, "visible": true, "backgroundColor": "", "fillRule": "nonzero", "paintFirst": "fill", "globalCompositeOperation": "source-over", "skewX": 0, "skewY": 0, "rx": 0, "ry": 0}, {"type": "rect", "version": "4.4.0", "originX": "left", "originY": "top", "left": 502, "top": 78, "width": 217, "height": 17, "fill": "rgba(200, 169, 110, 0.15)", "stroke": "#c8a96e", "strokeWidth": 2, "strokeDashArray": null, "strokeLineCap": "butt", "strokeDashOffset": 0, "strokeLineJoin": "miter", "strokeUniform": true, "strokeMiterLimit": 4, "scaleX": 1, "scaleY": 1, "angle": 0, "flipX": false, "flipY": false, "opacity": 1, "shadow": null, "visible": true, "backgroundColor": "", "fillRule": "nonzero", "paintFirst": "fill", "globalCompositeOperation": "source-over", "skewX": 0, "skewY": 0, "rx": 0, "ry": 0}, {"type": "rect", "version": "4.4.0", "originX": "left", "originY": "top", "left": 566, "top": 91, "width": 147, "height": 14, "fill": "rgba(200, 169, 110, 0.15)", "stroke": "#c8a96e", "strokeWidth": 2, "strokeDashArray": null, "strokeLineCap": "butt", "strokeDashOffset": 0, "strokeLineJoin": "miter", "strokeUniform": true, "strokeMiterLimit": 4, "scaleX": 1, "scaleY": 1, "angle": 0, "flipX": false, "flipY": false, "opacity": 1, "shadow": null, "visible": true, "backgroundColor": "", "fillRule": "nonzero", "paintFirst": "fill", "globalCompositeOperation": "source-over", "skewX": 0, "skewY": 0, "rx": 0, "ry": 0}, {"type": "rect", "version": "4.4.0", "originX": "left", "originY": "top", "left": 496, "top": 103, "width": 221, "height": 14, "fill": "rgba(200, 169, 110, 0.15)", "stroke": "#c8a96e", "strokeWidth": 2, "strokeDashArray": null, "strokeLineCap": "butt", "strokeDashOffset": 0, "strokeLineJoin": "miter", "strokeUniform": true, "strokeMiterLimit": 4, "scaleX": 1, "scaleY": 1, "angle": 0, "flipX": false, "flipY": false, "opacity": 1, "shadow": null, "visible": true, "backgroundColor": "", "fillRule": "nonzero", "paintFirst": "fill", "globalCompositeOperation": "source-over", "skewX": 0, "skewY": 0, "rx": 0, "ry": 0}]}