{"version": "4.4.0", "objects": [{"type": "rect", "version": "4.4.0", "originX": "left", "originY": "top", "left": 56.01, "top": 16, "width": 703, "height": 29, "fill": "rgba(200, 169, 110, 0.15)", "stroke": "#c8a96e", "strokeWidth": 2, "strokeDashArray": null, "strokeLineCap": "butt", "strokeDashOffset": 0, "strokeLineJoin": "miter", "strokeUniform": true, "strokeMiterLimit": 4, "scaleX": 1.02, "scaleY": 1.41, "angle": 0, "flipX": false, "flipY": false, "opacity": 1, "shadow": null, "visible": true, "backgroundColor": "", "fillRule": "nonzero", "paintFirst": "fill", "globalCompositeOperation": "source-over", "skewX": 0, "skewY": 0, "rx": 0, "ry": 0}, {"type": "rect", "version": "4.4.0", "originX": "left", "originY": "top", "left": 19, "top": 94, "width": 747, "height": 25, "fill": "rgba(200, 169, 110, 0.15)", "stroke": "#c8a96e", "strokeWidth": 2, "strokeDashArray": null, "strokeLineCap": "butt", "strokeDashOffset": 0, "strokeLineJoin": "miter", "strokeUniform": true, "strokeMiterLimit": 4, "scaleX": 1, "scaleY": 1, "angle": 0, "flipX": false, "flipY": false, "opacity": 1, "shadow": null, "visible": true, "backgroundColor": "", "fillRule": "nonzero", "paintFirst": "fill", "globalCompositeOperation": "source-over", "skewX": 0, "skewY": 0, "rx": 0, "ry": 0}, {"type": "rect", "version": "4.4.0", "originX": "left", "originY": "top", "left": 21, "top": 141, "width": 752, "height": 34, "fill": "rgba(200, 169, 110, 0.15)", "stroke": "#c8a96e", "strokeWidth": 2, "strokeDashArray": null, "strokeLineCap": "butt", "strokeDashOffset": 0, "strokeLineJoin": "miter", "strokeUniform": true, "strokeMiterLimit": 4, "scaleX": 1, "scaleY": 1, "angle": 0, "flipX": false, "flipY": false, "opacity": 1, "shadow": null, "visible": true, "backgroundColor": "", "fillRule": "nonzero", "paintFirst": "fill", "globalCompositeOperation": "source-over", "skewX": 0, "skewY": 0, "rx": 0, "ry": 0}, {"type": "rect", "version": "4.4.0", "originX": "left", "originY": "top", "left": 19, "top": 190, "width": 757, "height": 45, "fill": "rgba(200, 169, 110, 0.15)", "stroke": "#c8a96e", "strokeWidth": 2, "strokeDashArray": null, "strokeLineCap": "butt", "strokeDashOffset": 0, "strokeLineJoin": "miter", "strokeUniform": true, "strokeMiterLimit": 4, "scaleX": 1, "scaleY": 1, "angle": 0, "flipX": false, "flipY": false, "opacity": 1, "shadow": null, "visible": true, "backgroundColor": "", "fillRule": "nonzero", "paintFirst": "fill", "globalCompositeOperation": "source-over", "skewX": 0, "skewY": 0, "rx": 0, "ry": 0}, {"type": "rect", "version": "4.4.0", "originX": "left", "originY": "top", "left": 18, "top": 274, "width": 318, "height": 33, "fill": "rgba(200, 169, 110, 0.15)", "stroke": "#c8a96e", "strokeWidth": 2, "strokeDashArray": null, "strokeLineCap": "butt", "strokeDashOffset": 0, "strokeLineJoin": "miter", "strokeUniform": true, "strokeMiterLimit": 4, "scaleX": 1, "scaleY": 1, "angle": 0, "flipX": false, "flipY": false, "opacity": 1, "shadow": null, "visible": true, "backgroundColor": "", "fillRule": "nonzero", "paintFirst": "fill", "globalCompositeOperation": "source-over", "skewX": 0, "skewY": 0, "rx": 0, "ry": 0}]}